django_geocoding/__init__.py
django_geocoding/app_settings.py
django_geocoding/apps.py
django_geocoding/cli.py
django_geocoding/factories.py
django_geocoding/forms.py
django_geocoding/models.py
django_geocoding/resources.py
django_geocoding/urls.py
django_geocoding/backends/__init__.py
django_geocoding/backends/opencage.py
django_geocoding/locales/.gitignore
django_geocoding/locales/babel.cfg
django_geocoding/management/commands/__init__.py
django_geocoding/migrations/__init__.py
django_geocoding/static/django_geocoding/css/django_geocoding.css
django_geocoding/static/django_geocoding/img/.gitignore
django_geocoding/static/django_geocoding/js/django_geocoding.js
django_geocoding/templates/django_geocoding/base.html
django_geocoding-0.1.1.dist-info/DESCRIPTION.rst
django_geocoding-0.1.1.dist-info/METADATA
django_geocoding-0.1.1.dist-info/RECORD
django_geocoding-0.1.1.dist-info/WHEEL
django_geocoding-0.1.1.dist-info/entry_points.txt
django_geocoding-0.1.1.dist-info/metadata.json
django_geocoding-0.1.1.dist-info/top_level.txt
