Metadata-Version: 2.0
Name: django-geocoding
Version: 0.1.1
Summary: Abstract base models and mixins to store address and GPS coordinates info
Home-page: https://github.com/wooyek/django-geocoding
Author: Janusz Skonieczny
Author-email: js+pypi@bravelabs.pl
License: MIT license
Keywords: django-geocoding
Platform: UNKNOWN
Classifier: Development Status :: 3 - Alpha
Classifier: Framework :: Django :: 1.10
Classifier: Intended Audience :: Developers
Classifier: License :: OSI Approved :: MIT License
Classifier: Natural Language :: English
Classifier: Programming Language :: Python :: 2.7
Classifier: Programming Language :: Python :: 3.5
Requires-Python: >=2.7
Requires-Dist: click
Requires-Dist: django-environ
Requires-Dist: django-formtools
Requires-Dist: django-import-export
Requires-Dist: django-localflavor
Requires-Dist: django-pascal-templates
Requires-Dist: django-powerbank
Requires-Dist: opencage
Requires-Dist: psycopg2
Requires-Dist: pycountry
Requires-Dist: pytz
Requires-Dist: requests
Requires-Dist: django (>=1.8)
Requires-Dist: pathlib; python_version < "3.3"
Requires-Dist: enum34; python_version < "3.4"
Requires-Dist: django (<2.0); python_version < "3.5"
Requires-Dist: django (>=2.0); python_version >= "3.5"
Provides-Extra: factories
Requires-Dist: factory-boy; extra == 'factories'
